Metadata-Version: 2.1
Name: odoo13-addon-purchase-variant-configurator-on-confirm
Version: 13.0.1.0.1.dev10
Summary: Create product variants when confirming the purchase order
Home-page: https://github.com/OCA/product-variant
Author: AvanzOSC, Tecnativa, ACSONE SA/NV, Odoo Community Association (OCA)
Author-email: support@odoo-community.org
License: AGPL-3
Platform: UNKNOWN
Classifier: Programming Language :: Python
Classifier: Framework :: Odoo
Classifier: Framework :: Odoo :: 13.0
Classifier: License :: OSI Approved :: GNU Affero General Public License v3
Requires-Python: >=3.5
Requires-Dist: odoo13-addon-purchase-variant-configurator
Requires-Dist: odoo <13.1dev,>=13.0a
